crawl_youtube_channel/__init__.py
crawl_youtube_channel/audio.py
crawl_youtube_channel/channel.py
crawl_youtube_channel/cli.py
crawl_youtube_channel/comments.py
crawl_youtube_channel/crawl_channel.py
crawl_youtube_channel/data.py
crawl_youtube_channel/meta.py
crawl_youtube_channel/transcript.py
crawl_youtube_channel/util.py
crawl_youtube_channel/video.py
crawl_youtube_channel-0.0.1.dist-info/licenses/LICENSE
crawl_youtube_channel-0.0.1.dist-info/METADATA
crawl_youtube_channel-0.0.1.dist-info/WHEEL
crawl_youtube_channel-0.0.1.dist-info/entry_points.txt
crawl_youtube_channel-0.0.1.dist-info/top_level.txt
crawl_youtube_channel-0.0.1.dist-info/RECORD
