Metadata-Version: 2.4
Name: crawl-youtube-channel
Version: 0.0.1
Summary: A package to crawl a youtube channel
Home-page: 
Author: Daniel Olson
Author-email: daniel@orphos.cloud
Keywords: youtube crawl crawler channel
Classifier: Development Status :: 3 - Alpha
Classifier: Intended Audience :: Developers
Classifier: License :: OSI Approved :: MIT License
Classifier: Operating System :: OS Independent
Classifier: Programming Language :: Python :: 3
Classifier: Programming Language :: Python :: 3.10
Classifier: Programming Language :: Python :: 3.11
Classifier: Programming Language :: Python :: 3.12
Requires-Python: >=3.10
License-File: LICENSE
Requires-Dist: youtube-transcript-api
Requires-Dist: google-api-python-client
Requires-Dist: yt-dlp
Requires-Dist: python-dotenv
Requires-Dist: crawl4ai
Dynamic: author
Dynamic: author-email
Dynamic: classifier
Dynamic: description
Dynamic: description-content-type
Dynamic: keywords
Dynamic: license-file
Dynamic: requires-dist
Dynamic: requires-python
Dynamic: summary
